medspacy_io/__init__.py
medspacy_io/version.py
medspacy_io/consumer/__init__.py
medspacy_io/consumer/demo_consumer.py
medspacy_io/consumer/doc_consumer.py
medspacy_io/reader/__init__.py
medspacy_io/reader/base_reader.py
medspacy_io/reader/ehost_reader.py
medspacy_io/vectorizer/Vectorizer.py
medspacy_io/vectorizer/__init__.py
medspacy_io/writer/__init__.py
medspacy_io/writer/ehost_writer.py
medspacy_io-0.1.0.dev34.dist-info/LICENSE
medspacy_io-0.1.0.dev34.dist-info/METADATA
medspacy_io-0.1.0.dev34.dist-info/WHEEL
medspacy_io-0.1.0.dev34.dist-info/top_level.txt
medspacy_io-0.1.0.dev34.dist-info/RECORD
